pythonejs/__init__.py
pythonejs/engine.py
pythonejs-0.1.0.dist-info/METADATA
pythonejs-0.1.0.dist-info/WHEEL
pythonejs-0.1.0.dist-info/top_level.txt
pythonejs-0.1.0.dist-info/RECORD
