Metadata-Version: 2.1
Name: pythonejs
Version: 0.1.0
Summary: A simple EJS-like template engine for Python
Home-page: https://github.com/calteen/pythonejs
Author: jay
Author-email: pjay32547@gmail.com
Classifier: Programming Language :: Python :: 3
Classifier: License :: OSI Approved :: MIT License
Classifier: Operating System :: OS Independent
Requires-Python: >=3.6
